heimdall/__init__.py
heimdall/__main__.py
heimdall/_version.py
heimdall/create_client.py
heimdall/exceptions.py
heimdall/heimdall_client.py
heimdall/cli/__init__.py
heimdall/cli/cli_common.py
heimdall/cli/connect.py
heimdall/cli/isf.py
heimdall/cli/isf_manager.py
heimdall/core/__init__.py
heimdall/core/access.py
heimdall/core/context.py
heimdall/core/descriptors.py
heimdall/core/isf_file.py
heimdall/core/symbol.py
heimdall/core/symbols_jar.py
heimdall/os_related/__init__.py
heimdall/os_related/base_os/__init__.py
heimdall/os_related/base_os/kernel_struct.py
heimdall/os_related/base_os/processes.py
heimdall/os_related/linux/__init__.py
heimdall/os_related/linux/filesystem.py
heimdall/os_related/linux/linux_client.py
heimdall/os_related/linux/processes.py
heimdall/os_related/macos/__init__.py
heimdall/os_related/macos/filesystem.py
heimdall/os_related/macos/macos_client.py
heimdall/os_related/macos/processes.py
heimdall/os_related/windows/__init__.py
heimdall/os_related/windows/processes.py
heimdall/os_related/windows/windows_client.py
heimdall/utils/__init__.py
heimdall/utils/utils.py
heimdall_vmi-0.0.2.dist-info/LICENSE
heimdall_vmi-0.0.2.dist-info/METADATA
heimdall_vmi-0.0.2.dist-info/WHEEL
heimdall_vmi-0.0.2.dist-info/entry_points.txt
heimdall_vmi-0.0.2.dist-info/top_level.txt
heimdall_vmi-0.0.2.dist-info/RECORD
