Metadata-Version: 2.1
Name: heimdall-vmi
Version: 0.0.2
Summary: Vm introspection
Author-email: netanelc305 <netanelc305@protonmail.com>
Maintainer-email: netanelc305 <netanelc305@protonmail.com>
License: GNU GENERAL PUBLIC LICENSE
Classifier: Operating System :: POSIX :: Linux
Classifier: Development Status :: 5 - Production/Stable
Classifier: License :: OSI Approved :: GNU General Public License v3 or later (GPLv3+)
Classifier: Programming Language :: Python :: 3
Classifier: Programming Language :: Python :: 3.9
Classifier: Programming Language :: Python :: 3.10
Classifier: Programming Language :: Python :: 3.11
Classifier: Programming Language :: Python :: 3.12
Classifier: Programming Language :: Python :: 3.13
Classifier: Programming Language :: Python :: 3 :: Only
Requires-Python: >=3.9
License-File: LICENSE
Requires-Dist: click
Requires-Dist: coloredlogs
Requires-Dist: inquirer3
Requires-Dist: requests
Requires-Dist: tqdm
Requires-Dist: ipython
Requires-Dist: traitlets
Requires-Dist: humanfriendly
Requires-Dist: capstone
Provides-Extra: test
Requires-Dist: pytest; extra == "test"
